{
    "Animals & Pet Supplies": [
      "Live Animals",
      "Pet Supplies"
    ],
    "Apparel & Accessories": [
      "Clothing",
      "Clothing Accessories",
      "Costumes & Accessories",
      "Handbag & Wallet Accessories",
      "Handbags, Wallets & Cases",
      "Jewelry",
      "Shoe Accessories",
      "Shoes"
    ],
    "Arts & Entertainment": [
      "Event Tickets",
      "Hobbies & Creative Arts",
      "Party & Celebration"
    ],
    "Baby & Toddler": [
      "Baby Bathing",
      "Baby Gift Sets",
      "Baby Health",
      "Baby Safety",
      "Baby Toys & Activity Equipment",
      "Baby Transport",
      "Baby Transport Accessories",
      "Diapering",
      "Nursing & Feeding",
      "Potty Training",
      "Swaddling & Receiving Blankets"
    ],
    "Business & Industrial": [
      "Advertising & Marketing",
      "Agriculture",
      "Automation Control Components",
      "Construction",
      "Dentistry",
      "Film & Television",
      "Finance & Insurance",
      "Food Service",
      "Forestry & Logging",
      "Hairdressing & Cosmetology",
      "Heavy Machinery",
      "Hotel & Hospitality",
      "Industrial Storage",
      "Industrial Storage Accessories",
      "Janitorial Carts & Caddies",
      "Law Enforcement",
      "Manufacturing",
      "Material Handling",
      "Medical",
      "Mining & Quarrying",
      "Piercing & Tattooing",
      "Retail",
      "Science & Laboratory",
      "Signage",
      "Work Safety Protective Gear"
    ],
    "Cameras & Optics": [
      "Camera & Optic Accessories",
      "Cameras",
      "Optics",
      "Photography"
    ],
    "Electronics": [
      "Arcade Equipment",
      "Audio",
      "Circuit Boards & Components",
      "Communications",
      "Components",
      "Computers",
      "Electronics Accessories",
      "GPS Accessories",
      "GPS Navigation Systems",
      "GPS Tracking Devices",
      "Marine Electronics",
      "Networking",
      "Print, Copy, Scan & Fax",
      "Radar Detectors",
      "Speed Radars",
      "Toll Collection Devices",
      "Video",
      "Video Game Console Accessories",
      "Video Game Consoles"
    ],
    "Food, Beverages & Tobacco": [
      "Beverages",
      "Food Items",
      "Tobacco Products"
    ],
    "Furniture": [
      "Baby & Toddler Furniture",
      "Beds & Accessories",
      "Benches",
      "Cabinets & Storage",
      "Carts & Islands",
      "Chair Accessories",
      "Chairs",
      "Entertainment Centers & TV Stands",
      "Furniture Sets",
      "Futon Frames",
      "Futon Pads",
      "Futons",
      "Office Furniture",
      "Office Furniture Accessories",
      "Ottomans",
      "Outdoor Furniture",
      "Outdoor Furniture Accessories",
      "Room Divider Accessories",
      "Room Dividers",
      "Shelving",
      "Shelving Accessories",
      "Sofa Accessories",
      "Sofas",
      "Table Accessories",
      "Tables"
    ],
    "Hardware": [
      "Building Consumables",
      "Building Materials",
      "Fencing & Barriers",
      "Fuel",
      "Fuel Containers & Tanks",
      "Hardware Accessories",
      "Hardware Pumps",
      "Heating, Ventilation & Air Conditioning",
      "Locks & Keys",
      "Plumbing",
      "Power & Electrical Supplies",
      "Small Engines",
      "Storage Tanks",
      "Tool Accessories",
      "Tools"
    ],
    "Health & Beauty": [
      "Health Care",
      "Jewelry Cleaning & Care",
      "Personal Care"
    ],
    "Home & Garden": [
      "Bathroom Accessories",
      "Business & Home Security",
      "Decor",
      "Emergency Preparedness",
      "Fireplace & Wood Stove Accessories",
      "Fireplaces",
      "Flood, Fire & Gas Safety",
      "Household Appliance Accessories",
      "Household Appliances",
      "Household Supplies",
      "Kitchen & Dining",
      "Lawn & Garden",
      "Lighting",
      "Lighting Accessories",
      "Linens & Bedding",
      "Parasols & Rain Umbrellas",
      "Plants",
      "Pool & Spa",
      "Smoking Accessories",
      "Umbrella Sleeves & Cases",
      "Wood Stoves"
    ],
    "Luggage & Bags": [
      "Backpacks",
      "Briefcases",
      "Cosmetic & Toiletry Bags",
      "Diaper Bags",
      "Dry Boxes",
      "Duffel Bags",
      "Fanny Packs",
      "Garment Bags",
      "Luggage Accessories",
      "Messenger Bags",
      "Shopping Totes",
      "Suitcases",
      "Train Cases"
    ],
    "Mature": [
      "Erotic",
      "Weapons"
    ],
    "Media": [
      "Books",
      "Carpentry & Woodworking Project Plans",
      "DVDs & Videos",
      "Magazines & Newspapers",
      "Music & Sound Recordings",
      "Product Manuals",
      "Sheet Music"
    ],
    "Office Supplies": [
      "Book Accessories",
      "Desk Pads & Blotters",
      "Filing & Organization",
      "General Office Supplies",
      "Impulse Sealers",
      "Lap Desks",
      "Name Plates",
      "Office & Chair Mats",
      "Office Carts",
      "Office Equipment",
      "Office Instruments",
      "Paper Handling",
      "Presentation Supplies",
      "Shipping Supplies"
    ],
    "Religious & Ceremonial": [
      "Memorial Ceremony Supplies",
      "Religious Items",
      "Wedding Ceremony Supplies"
    ],
    "Software": [
      "Computer Software",
      "Digital Goods & Currency",
      "Video Game Software"
    ],
    "Sporting Goods": [
      "Athletics",
      "Exercise & Fitness",
      "Indoor Games",
      "Outdoor Recreation"
    ],
    "Toys & Games": [
      "Game Timers",
      "Games",
      "Outdoor Play Equipment",
      "Puzzles",
      "Toys"
    ],
    "Vehicles & Parts": [
      "Vehicle Parts & Accessories",
      "Vehicles"
    ],
    "": []
  }